nics/__main__.py
nics/main/__init__.py
nics/main/constants.py
nics/main/_template/docs/404.md
nics/main/_template/docs/favicon.png
nics/main/_template/docs/tree/1 - Page1.md
nics/main/_template/docs/tree/8 - Changelog.md
nics/main/_template/docs/tree/9 - About.md
nics/main/_template/docs/tree/index.md
nics/main/_template/docs/tree/2 - Pages/baz.md
nics/main/_template/docs/tree/2 - Pages/logo200.png
nics/main/_template/docs/tree/7 - FAQs/1 - Question1.md
nics/main/_template/docs/tree/7 - FAQs/index.md
nics/main/_template/web/_layouts/main.html
nics/main/_template/web/_sass/footer.scss
nics/main/_template/web/_sass/header.scss
nics/main/_template/web/_sass/main.scss
nics/main/_template/web/_sass/sass-code-highlight.scss
nics/main/_template/web/scripts/header.js
nics/main/compile/__init__.py
nics/main/compile/copying_template.py
nics/main/compile/inspect.py
nics/main/compile/update_404_and_favicon.py
nics/main/compile/update_docs_tree.py
nics/main/compile/update_footer.py
nics/main/compile/update_header.py
nics/main/compile/update_jekyll_config.py
nics/main/compile/update_sass_constants.py
nics/main/upgrade/__init__.py
nics/main/wizard/__init__.py
nics/main/wizard/settings_writer.py
nics/main/wizard/workflow_writer.py
nics-2.8.4.dist-info/LICENSE
nics-2.8.4.dist-info/METADATA
nics-2.8.4.dist-info/WHEEL
nics-2.8.4.dist-info/entry_points.txt
nics-2.8.4.dist-info/top_level.txt
nics-2.8.4.dist-info/RECORD
